pyapollo/__init__.py
pyapollo/async_client.py
pyapollo/async_interface.py
pyapollo/client.py
pyapollo/exceptions.py
pyapollo/interface.py
pyapollo/settings.py
pyapollo_zenkilan-0.2.0.dist-info/licenses/LICENSE
pyapollo_zenkilan-0.2.0.dist-info/METADATA
pyapollo_zenkilan-0.2.0.dist-info/WHEEL
pyapollo_zenkilan-0.2.0.dist-info/top_level.txt
pyapollo_zenkilan-0.2.0.dist-info/RECORD
