Metadata-Version: 2.4
Name: pyapollo-zenkilan
Version: 0.2.0
Summary: Apollo client with async support and pydantic integration, tested on python 3.13
Home-page: https://github.com/OuterCloud/pyapollo
Author: lantianyou
Author-email: lantianyou <434209210@qq.com>
Maintainer-email: lantianyou <434209210@qq.com>
License-Expression: MIT
Project-URL: Homepage, https://github.com/OuterCloud/pyapollo
Project-URL: Documentation, https://github.com/OuterCloud/pyapollo#readme
Project-URL: Repository, https://github.com/OuterCloud/pyapollo
Project-URL: Issues, https://github.com/OuterCloud/pyapollo/issues
Project-URL: Changelog, https://github.com/OuterCloud/pyapollo/blob/main/README.md
Keywords: apollo,configuration,async,client,pydantic
Classifier: Development Status :: 4 - Beta
Classifier: Intended Audience :: Developers
Classifier: Programming Language :: Python :: 3
Classifier: Programming Language :: Python :: 3.7
Classifier: Programming Language :: Python :: 3.8
Classifier: Programming Language :: Python :: 3.9
Classifier: Programming Language :: Python :: 3.10
Classifier: Programming Language :: Python :: 3.11
Classifier: Programming Language :: Python :: 3.12
Classifier: Programming Language :: Python :: 3.13
Classifier: Framework :: AsyncIO
Classifier: Topic :: Software Development :: Libraries :: Python Modules
Classifier: Topic :: System :: Distributed Computing
Requires-Python: >=3.7
License-File: LICENSE
Requires-Dist: setuptools>=61.0
Requires-Dist: requests>=2.25.0
Requires-Dist: loguru>=0.5.0
Requires-Dist: aiohttp>=3.7.0
Requires-Dist: aiofiles>=0.6.0
Requires-Dist: pydantic-settings>=2.0.0
Dynamic: author
Dynamic: home-page
Dynamic: license-file
Dynamic: requires-python
